MANIFEST.in
README.txt
setup.cfg
setup.py
docs/HISTORY.txt
horae/__init__.py
horae.planning.egg-info/PKG-INFO
horae.planning.egg-info/SOURCES.txt
horae.planning.egg-info/dependency_links.txt
horae.planning.egg-info/entry_points.txt
horae.planning.egg-info/namespace_packages.txt
horae.planning.egg-info/not-zip-safe
horae.planning.egg-info/requires.txt
horae.planning.egg-info/top_level.txt
horae/planning/__init__.py
horae/planning/calculation.py
horae/planning/calendaring.py
horae/planning/catalog.py
horae/planning/configure.zcml
horae/planning/events.py
horae/planning/execution.py
horae/planning/extenders.py
horae/planning/interfaces.py
horae/planning/notification.py
horae/planning/permissions.py
horae/planning/planning.py
horae/planning/properties.py
horae/planning/resource.py
horae/planning/upgrade.py
horae/planning/viewlets.py
horae/planning/views.py
horae/planning/locales/horae.planning.pot
horae/planning/locales/de/LC_MESSAGES/horae.planning.mo
horae/planning/locales/de/LC_MESSAGES/horae.planning.po
horae/planning/static/graph.js
horae/planning/static/plan.js
horae/planning/static/planning.css
horae/planning/templates/overview.cpt
horae/planning/templates/resolveconflicts.cpt
horae/planning/templates/resource.cpt
horae/planning/viewlet_templates/resourceinfo.cpt