Metadata-Version: 1.0
Name: horae.planning
Version: 1.0a1
Summary: Provides resource planning functionality for the Horae resource planning system
Home-page: UNKNOWN
Author: Simon Kaeser
Author-email: skaeser@gmail.com
License: GPL
Platform: UNKNOWN
Classifier: Programming Language :: Python
